NoxmainNetwork/__init__.py
NoxmainNetwork-1.7.2.dist-info/LICENSE
NoxmainNetwork-1.7.2.dist-info/METADATA
NoxmainNetwork-1.7.2.dist-info/WHEEL
NoxmainNetwork-1.7.2.dist-info/top_level.txt
NoxmainNetwork-1.7.2.dist-info/RECORD
