Metadata-Version: 2.1
Name: NoxmainNetwork
Version: 1.7.2
Summary: A package to create, train and test neural networks with mutiple layers
Home-page: https://github.com/Noxmain/NoxmainNetwork
Author: Noxmain
Author-email: noah.finalcut@gmail.com
License: MIT
Platform: UNKNOWN
Classifier: Programming Language :: Python :: 3
Classifier: License :: OSI Approved :: MIT License
Classifier: Operating System :: OS Independent
